{
  "policies": {
    "Reliable": {
      "maxAttempts": 5,
      "delaysMs": [1000, 5000, 30000, 60000, 300000], 
      "routeToDlq": true
    },
    "Fast": {
      "maxAttempts": 2,
      "delaysMs": [2000, 10000],
      "routeToDlq": false
    },
    "Payment": {
      "maxAttempts": 7,
      "delaysMs": [5000, 30000, 60000, 120000, 300000, 600000, 1800000],
      "routeToDlq": true
    }
  },
  "mappings": {
    "OrderCreated": "Reliable",
    "OrderCancelled": "Reliable",
    "PaymentAuthorized": "Payment",
    "PaymentFailed": "Payment",
    "PaymentRequested": "Payment",
    "NotificationSent": "Fast",
    "default": "Reliable"
  }
}
